metadsl_core/__init__.py
metadsl_core/abstraction.py
metadsl_core/abstraction_test.py
metadsl_core/boolean.py
metadsl_core/boolean_test.py
metadsl_core/conversion.py
metadsl_core/conversion_test.py
metadsl_core/either.py
metadsl_core/either_test.py
metadsl_core/function.py
metadsl_core/function_test.py
metadsl_core/integer.py
metadsl_core/maybe.py
metadsl_core/maybe_test.py
metadsl_core/pair.py
metadsl_core/pair_test.py
metadsl_core/strategies.py
metadsl_core/vec.py
metadsl_core/vec_test.py
metadsl_core-0.4.0.dist-info/WHEEL
metadsl_core-0.4.0.dist-info/METADATA
metadsl_core-0.4.0.dist-info/RECORD
